{
  "source_id": "mira-rojanasakul",
  "last_article": {
    "title": "The decline of the Thwaites Glacier could affect tens of millions worldwide.",
    "url": "https://www.nytimes.com/live/2025/climate/antarctica-thwaites-glacier/the-decline-of-the-thwaites-glacier-could-affect-tens-of-millions-worldwide",
    "published_time": null
  },
  "last_checked": "2026-05-26T19:11:52.764319Z",
  "etag": null,
  "last_modified": "Tue, 26 May 2026 19:11:50 GMT",
  "error_count": 0,
  "last_error": null
}